heightcraft/main.py
heightcraft/cli/argument_parser.py
heightcraft/cli/commands.py
heightcraft/core/config.py
heightcraft/core/constants.py
heightcraft/core/exceptions.py
heightcraft/core/gpu.py
heightcraft/core/logging.py
heightcraft/domain/height_map.py
heightcraft/domain/mesh.py
heightcraft/domain/point_cloud.py
heightcraft/infrastructure/cache_manager.py
heightcraft/infrastructure/file_storage.py
heightcraft/infrastructure/gpu_manager.py
heightcraft/infrastructure/height_map_repository.py
heightcraft/infrastructure/lidar_repository.py
heightcraft/infrastructure/model_repository.py
heightcraft/infrastructure/profiler.py
heightcraft/infrastructure/resource_manager.py
heightcraft/models/upscaler.py
heightcraft/processors/__init__.py
heightcraft/processors/base_processor.py
heightcraft/processors/image_processor.py
heightcraft/processors/large_model_processor.py
heightcraft/processors/lidar_processor.py
heightcraft/processors/standard_processor.py
heightcraft/services/height_map_service.py
heightcraft/services/mesh_service.py
heightcraft/services/model_service.py
heightcraft/services/point_cloud_service.py
heightcraft/services/sampling_service.py
heightcraft/services/training_service.py
heightcraft/services/upscaling_service.py
heightcraft/utils/converters.py
heightcraft/utils/data_converter.py
heightcraft/utils/input_validator.py
heightcraft/utils/resolution_calculator.py
heightcraft/utils/threading.py
heightcraft/utils/validators.py
heightcraft-2.0.0.dist-info/METADATA
heightcraft-2.0.0.dist-info/WHEEL
heightcraft-2.0.0.dist-info/entry_points.txt
heightcraft-2.0.0.dist-info/licenses/LICENSE
heightcraft-2.0.0.dist-info/RECORD
