Metadata-Version: 2.4
Name: heightcraft
Version: 2.0.0
Summary: A powerful and flexible height map generator
Project-URL: Repository, https://github.com/andre-silva-14/heightcraft
Project-URL: Documentation, https://andre-silva-14.github.io/heightcraft/
Author-email: Heightcraft Team <info@heightcraft.com>
License: MIT
License-File: LICENSE
Keywords: 3D model,ai,height map,lidar,rendering,terrain,upscaling,visualization
Classifier: Development Status :: 4 - Beta
Classifier: Intended Audience :: Developers
Classifier: Intended Audience :: Science/Research
Classifier: License :: OSI Approved :: MIT License
Classifier: Programming Language :: Python :: 3
Classifier: Programming Language :: Python :: 3.8
Classifier: Programming Language :: Python :: 3.9
Classifier: Topic :: Multimedia :: Graphics :: 3D Modeling
Classifier: Topic :: Multimedia :: Graphics :: 3D Rendering
Classifier: Topic :: Scientific/Engineering :: Visualization
Requires-Python: >=3.8
Requires-Dist: laspy[lazrs]>=2.0.0
Requires-Dist: matplotlib>=3.3.4
Requires-Dist: numpy>=1.19.5
Requires-Dist: pillow>=9.0.0
Requires-Dist: psutil>=5.9.0
Requires-Dist: scipy
Requires-Dist: tifffile>=2023.0.0
Requires-Dist: torch
Requires-Dist: trimesh>=4.0.0
Requires-Dist: xxhash>=3.0.0
